hpOneView/__init__.py
hpOneView/connection.py
hpOneView/exceptions.py
hpOneView/oneview_client.py
hpOneView/image_streamer/__init__.py
hpOneView/image_streamer/image_streamer_client.py
hpOneView/image_streamer/resources/__init__.py
hpOneView/image_streamer/resources/artifact_bundles.py
hpOneView/image_streamer/resources/build_plans.py
hpOneView/image_streamer/resources/deployment_groups.py
hpOneView/image_streamer/resources/deployment_plans.py
hpOneView/image_streamer/resources/golden_images.py
hpOneView/image_streamer/resources/os_volumes.py
hpOneView/image_streamer/resources/plan_scripts.py
hpOneView/resources/__init__.py
hpOneView/resources/resource.py
hpOneView/resources/task_monitor.py
hpOneView/resources/activity/__init__.py
hpOneView/resources/activity/alerts.py
hpOneView/resources/activity/events.py
hpOneView/resources/activity/tasks.py
hpOneView/resources/data_services/__init__.py
hpOneView/resources/data_services/metric_streaming.py
hpOneView/resources/facilities/__init__.py
hpOneView/resources/facilities/datacenters.py
hpOneView/resources/facilities/power_devices.py
hpOneView/resources/facilities/racks.py
hpOneView/resources/fc_sans/__init__.py
hpOneView/resources/fc_sans/endpoints.py
hpOneView/resources/fc_sans/managed_sans.py
hpOneView/resources/fc_sans/san_managers.py
hpOneView/resources/networking/__init__.py
hpOneView/resources/networking/connection_templates.py
hpOneView/resources/networking/ethernet_networks.py
hpOneView/resources/networking/fabrics.py
hpOneView/resources/networking/fc_networks.py
hpOneView/resources/networking/fcoe_networks.py
hpOneView/resources/networking/interconnect_link_topologies.py
hpOneView/resources/networking/interconnect_types.py
hpOneView/resources/networking/interconnects.py
hpOneView/resources/networking/internal_link_sets.py
hpOneView/resources/networking/logical_downlinks.py
hpOneView/resources/networking/logical_interconnect_groups.py
hpOneView/resources/networking/logical_interconnects.py
hpOneView-5.0.0.dist-info/LICENSE
hpOneView-5.0.0.dist-info/METADATA
hpOneView-5.0.0.dist-info/WHEEL
hpOneView-5.0.0.dist-info/top_level.txt
hpOneView-5.0.0.dist-info/RECORD
