Metadata-Version: 2.1
Name: hpOneView
Version: 5.0.0
Summary: HPE OneView Python Library
Home-page: https://github.com/HewlettPackard/oneview-python
Author: Hewlett Packard Enterprise Development LP
Author-email: oneview-pythonsdk@hpe.com
License: Apache
Download-URL: https://github.com/HewlettPackard/oneview-python/tarball/v5.0.0
Keywords: oneview,hpe
Platform: UNKNOWN
Requires-Dist: future (>=0.15.2)
